graphviz_static/__init__.py
graphviz_static/main.py
graphviz_static/bin/linux/aarch64/bin/dot
graphviz_static/bin/linux/aarch64/bin/dot2gxl
graphviz_static/bin/linux/aarch64/bin/dot_builtins
graphviz_static/bin/linux/aarch64/bin/dotty
graphviz_static/bin/linux/arm64/bin/dot
graphviz_static/bin/linux/arm64/bin/dot2gxl
graphviz_static/bin/linux/arm64/bin/dot_builtins
graphviz_static/bin/linux/arm64/bin/dotty
graphviz_static/bin/win/x64/ANN.dll
graphviz_static/bin/win/x64/acyclic.exe
graphviz_static/bin/win/x64/bcomps.exe
graphviz_static/bin/win/x64/brotlicommon.dll
graphviz_static/bin/win/x64/brotlidec.dll
graphviz_static/bin/win/x64/bz2.dll
graphviz_static/bin/win/x64/cairo-2.dll
graphviz_static/bin/win/x64/ccomps.exe
graphviz_static/bin/win/x64/cdt.dll
graphviz_static/bin/win/x64/cgraph++.dll
graphviz_static/bin/win/x64/cgraph.dll
graphviz_static/bin/win/x64/circo.exe
graphviz_static/bin/win/x64/cluster.exe
graphviz_static/bin/win/x64/concrt140.dll
graphviz_static/bin/win/x64/config8
graphviz_static/bin/win/x64/diffimg.exe
graphviz_static/bin/win/x64/dijkstra.exe
graphviz_static/bin/win/x64/dot.exe
graphviz_static/bin/win/x64/dot2gxl.exe
graphviz_static/bin/win/x64/dot_builtins.exe
graphviz_static/bin/win/x64/dot_sandbox
graphviz_static/bin/win/x64/edgepaint.exe
graphviz_static/bin/win/x64/fdp.exe
graphviz_static/bin/win/x64/ffi-8.dll
graphviz_static/bin/win/x64/fontconfig-1.dll
graphviz_static/bin/win/x64/freetype.dll
graphviz_static/bin/win/x64/fribidi-0.dll
graphviz_static/bin/win/x64/gc.exe
graphviz_static/bin/win/x64/gdtclft.dll
graphviz_static/bin/win/x64/getopt.dll
graphviz_static/bin/win/x64/gio-2.0-0.dll
graphviz_static/bin/win/x64/glib-2.0-0.dll
graphviz_static/bin/win/x64/gml2gv.exe
graphviz_static/bin/win/x64/gmodule-2.0-0.dll
graphviz_static/bin/win/x64/gobject-2.0-0.dll
graphviz_static/bin/win/x64/graphml2gv.exe
graphviz_static/bin/win/x64/gts.dll
graphviz_static/bin/win/x64/gv2gml.exe
graphviz_static/bin/win/x64/gv2gxl.exe
graphviz_static-0.2.5.dist-info/licenses/LICENSE
graphviz_static-0.2.5.dist-info/METADATA
graphviz_static-0.2.5.dist-info/WHEEL
graphviz_static-0.2.5.dist-info/top_level.txt
graphviz_static-0.2.5.dist-info/RECORD
