Metadata-Version: 2.4
Name: graphviz-static
Version: 0.2.5
Summary: A Graphviz static wrapper for Python
Home-page: https://github.com/tbtn123/graphviz-static
Author: Hvd/tbtn123/toibithieunang123
License: MIT
Project-URL: Homepage, https://github.com/tbtn123/graphviz-static
Project-URL: Repository, https://github.com/tbtn123/graphviz-static
Classifier: Development Status :: 3 - Alpha
Classifier: Intended Audience :: Developers
Classifier: License :: OSI Approved :: MIT License
Classifier: Programming Language :: Python :: 3
Classifier: Programming Language :: Python :: 3.6
Classifier: Programming Language :: Python :: 3.7
Classifier: Programming Language :: Python :: 3.8
Classifier: Programming Language :: Python :: 3.9
Classifier: Programming Language :: Python :: 3.10
Classifier: Programming Language :: Python :: 3.11
Requires-Python: >=3.6
License-File: LICENSE
Dynamic: home-page
Dynamic: license-file
Dynamic: requires-python
